{"bugs":[{"severity":"S3","op_sys":"macOS","status":"RESOLVED","component":"Theme","last_change_time":"2024-06-28T09:36:11Z","id":1606631,"priority":"P3","summary":"Inefficient z-ordering of elements in the browser UI, causes large layers with current WebRender heuristics","creation_time":"2020-01-02T13:46:45Z","keywords":["perf:resource-use"],"resolution":"INCOMPLETE"},{"id":1709763,"priority":"--","summary":"Menus show a delay of 4-5 seconds on mouse input (Wayland/WebRnender?)","last_change_time":"2024-05-06T19:32:16Z","keywords":["perf","perf:responsiveness"],"resolution":"INACTIVE","creation_time":"2021-05-06T04:02:44Z","op_sys":"Unspecified","status":"RESOLVED","component":"Graphics: WebRender","severity":"S3"},{"creation_time":"2022-04-24T19:22:21Z","keywords":["perf:responsiveness"],"resolution":"","last_change_time":"2024-09-07T03:37:01Z","id":1766181,"priority":"--","summary":"Firefox becomes really slow to respond/switch to on MacBook Pro M1 Max","severity":"--","op_sys":"Unspecified","status":"UNCONFIRMED","component":"Performance"},{"summary":"Slow rendering and opening of certain PDF types","component":"PDF Viewer","priority":"P3","status":"RESOLVED","id":1785979,"op_sys":"Unspecified","last_change_time":"2024-05-02T16:48:19Z","severity":"S3","resolution":"WORKSFORME","keywords":["regression"],"creation_time":"2022-08-19T06:50:58Z"},{"keywords":[],"resolution":"","creation_time":"2022-12-12T19:01:50Z","priority":"--","id":1805255,"status":"NEW","op_sys":"Unspecified","summary":"Firefox has 50% more soft page faults than Chrome running Speedometer 2","component":"Performance","last_change_time":"2024-03-13T14:34:04Z","severity":"--"},{"creation_time":"2023-04-05T14:45:37Z","resolution":"","keywords":["webcompat:platform-bug"],"last_change_time":"2024-09-16T21:56:00Z","severity":"S3","component":"Graphics: WebRender","summary":"CSS filter() with invert() and hue-rotate() results in sluggish scrolling on Wikipedia","op_sys":"Android","id":1826576,"status":"NEW","priority":"--"},{"last_change_time":"2023-12-04T12:24:31Z","summary":"GC overhead resulting 100% CPU usage and ending up freezes/hangs after each 30-60sec and occasionally panics on macOS","priority":"--","id":1830037,"creation_time":"2023-04-26T10:47:40Z","resolution":"INCOMPLETE","keywords":[],"severity":"S3","component":"Performance","op_sys":"Unspecified","status":"RESOLVED"},{"status":"RESOLVED","op_sys":"macOS","component":"Performance","severity":"--","priority":"--","id":1844961,"summary":"linkedin.com will crash the whole computer (El Capitain, Mac OS X 10.11.6) by using up the whole storage. The browser task (FirefoxCP Web Content) grows and grows in the GByte ranges.","last_change_time":"2024-05-06T19:53:32Z","keywords":[],"resolution":"INACTIVE","creation_time":"2023-07-22T23:26:31Z"},{"resolution":"DUPLICATE","keywords":[],"creation_time":"2023-11-22T14:21:41Z","summary":"Firefox freezes completely at irregular intervals","id":1866066,"priority":"--","last_change_time":"2024-03-01T21:22:53Z","component":"Disability Access APIs","op_sys":"Unspecified","status":"RESOLVED","severity":"--"},{"keywords":[],"resolution":"","creation_time":"2023-12-17T20:51:14Z","priority":"--","status":"UNCONFIRMED","id":1870532,"op_sys":"Unspecified","summary":"Firefox 120.0.1 grabs 100% of cpu resources and freezes","component":"Performance","last_change_time":"2024-02-27T18:30:44Z","severity":"--"},{"creation_time":"2023-12-25T13:00:34Z","keywords":[],"resolution":"INVALID","last_change_time":"2024-02-09T16:02:16Z","severity":"--","priority":"--","op_sys":"Unspecified","status":"RESOLVED","id":1871856,"summary":"Permanent increase of page memory usage under Ubuntu 22.04","component":"Performance"},{"severity":"--","last_change_time":"2024-07-01T12:23:26Z","summary":"Since the last update 121.0 Firefox uses insane amount of Ram 99% of my 32GB without any real reason and if it gets closed it buges out for 10 seconds spikes over the ram limit just to slowly close","component":"Performance","priority":"--","id":1872368,"status":"RESOLVED","op_sys":"Unspecified","creation_time":"2023-12-29T15:47:58Z","resolution":"INCOMPLETE","keywords":[]},{"creation_time":"2023-12-30T00:34:35Z","resolution":"INCOMPLETE","keywords":[],"last_change_time":"2024-07-01T12:25:21Z","summary":"Firefox lags after latest update, high memory use (121.0 12-2023)","priority":"--","id":1872414,"severity":"--","component":"Performance","op_sys":"Unspecified","status":"RESOLVED"},{"severity":"S3","status":"NEW","op_sys":"Unspecified","component":"PDF Viewer","creation_time":"2024-01-19T22:07:59Z","keywords":["perf"],"resolution":"","last_change_time":"2024-08-05T08:22:18Z","id":1875547,"priority":"P3","summary":"Slow (single-threaded) PDF rendering for documents with lots of vector shapes"},{"creation_time":"2024-01-26T11:03:08Z","keywords":["perf:resource-use","perf:responsiveness"],"resolution":"INCOMPLETE","last_change_time":"2024-08-05T12:18:30Z","id":1876708,"priority":"--","summary":"firefox using 3.4gb of memory with a few tabs open","severity":"--","op_sys":"Unspecified","status":"RESOLVED","component":"Performance"},{"status":"RESOLVED","op_sys":"Unspecified","component":"Performance","severity":"--","priority":"--","id":1877007,"summary":"extremely high CPU usage even with one tab open on the splash screen","last_change_time":"2024-08-05T12:18:25Z","keywords":["perf:resource-use"],"resolution":"INCOMPLETE","creation_time":"2024-01-28T16:15:06Z"},{"creation_time":"2024-02-07T20:00:44Z","keywords":["perf:resource-use"],"resolution":"INVALID","last_change_time":"2024-08-05T15:01:21Z","severity":"--","priority":"--","op_sys":"Unspecified","id":1879177,"status":"RESOLVED","summary":"3 youtube tabs are using 7GB of RAM","component":"Performance"},{"summary":"Firefox Freezes But Websites Don't","priority":"--","id":1879788,"last_change_time":"2024-03-13T14:26:26Z","resolution":"INCOMPLETE","keywords":[],"creation_time":"2024-02-12T02:38:12Z","component":"Performance","status":"RESOLVED","op_sys":"Unspecified","severity":"--"},{"resolution":"INCOMPLETE","keywords":["perf:resource-use"],"creation_time":"2024-02-12T17:13:40Z","summary":"firefox consuming 2 GB of RAM with 8 tabs open","component":"Performance","priority":"--","op_sys":"Unspecified","id":1879905,"status":"RESOLVED","severity":"--","last_change_time":"2024-09-02T12:20:43Z"},{"creation_time":"2024-02-29T23:13:16Z","resolution":"","keywords":[],"last_change_time":"2024-05-21T13:37:47Z","severity":"--","component":"Performance","summary":"Firefox consumes a lot of CPU and makes me Mac M2 hang for a good 15 seconds","status":"UNCONFIRMED","id":1882916,"op_sys":"Unspecified","priority":"--"},{"resolution":"INCOMPLETE","keywords":[],"creation_time":"2024-03-01T03:39:28Z","summary":"Firefox Browser Freezes when Opening Multiple Tabs","component":"Tabbed Browser","priority":"--","id":1882952,"op_sys":"Unspecified","status":"RESOLVED","last_change_time":"2024-09-02T12:21:23Z","severity":"--"},{"resolution":"INCOMPLETE","keywords":[],"creation_time":"2024-03-03T06:48:48Z","component":"Performance","summary":"firefox using large amount of memory","id":1883246,"status":"RESOLVED","op_sys":"Unspecified","priority":"--","last_change_time":"2024-09-02T12:20:29Z","severity":"--"},{"severity":"--","last_change_time":"2024-03-08T20:49:48Z","id":1883475,"op_sys":"Unspecified","status":"UNCONFIRMED","priority":"--","component":"Performance","summary":"huge amount of memory storage (constantly) idk why pls help/.................................................................................................................................................","creation_time":"2024-03-04T19:20:05Z","keywords":[],"resolution":""},{"severity":"--","last_change_time":"2024-03-08T20:49:58Z","priority":"--","id":1883507,"op_sys":"Unspecified","status":"UNCONFIRMED","summary":"Memory usage is too high 23GB and up to 60% CPU usage.","component":"Performance","creation_time":"2024-03-04T22:03:15Z","keywords":[],"resolution":""},{"op_sys":"Unspecified","status":"UNCONFIRMED","component":"Performance","severity":"--","keywords":[],"resolution":"","creation_time":"2024-03-05T15:09:26Z","priority":"--","id":1883669,"summary":"Memory Problem","last_change_time":"2024-03-08T20:50:27Z"},{"severity":"--","last_change_time":"2024-03-11T12:26:07Z","component":"Performance","summary":"Firefox is using lots of memory when only having several tabs open","status":"UNCONFIRMED","id":1884296,"op_sys":"Unspecified","priority":"--","creation_time":"2024-03-08T03:56:55Z","resolution":"","keywords":["memory-footprint"]},{"creation_time":"2024-03-17T18:24:37Z","resolution":"","keywords":[],"last_change_time":"2024-03-21T13:55:52Z","summary":"Use to many Ram","id":1885796,"priority":"--","severity":"--","component":"Performance","op_sys":"Unspecified","status":"UNCONFIRMED"},{"last_change_time":"2024-06-06T17:00:50Z","id":1891345,"priority":"--","summary":"Enourmous RAM usage (60Gig)","creation_time":"2024-04-14T09:00:25Z","keywords":[],"resolution":"","severity":"--","status":"UNCONFIRMED","op_sys":"Unspecified","component":"Performance"},{"creation_time":"2024-04-15T12:23:03Z","keywords":[],"resolution":"FIXED","last_change_time":"2024-04-26T08:53:42Z","severity":"--","priority":"--","op_sys":"Unspecified","id":1891462,"status":"RESOLVED","summary":"Update xsimd to new version 7eb009bca73e5cc51d05dcfcda25dfb74d6e0aaa from 2024-03-28 13:40:05","component":"Performance"},{"op_sys":"Windows 10","id":1891878,"status":"UNCONFIRMED","priority":"--","component":"Performance","summary":"I believe that Mozilla Firefox has memory leak issues.","last_change_time":"2024-07-04T03:17:33Z","severity":"--","keywords":[],"resolution":"","creation_time":"2024-04-16T22:39:55Z"},{"creation_time":"2024-04-23T23:06:49Z","resolution":"","keywords":[],"severity":"--","last_change_time":"2024-06-12T08:34:21Z","component":"Performance","summary":"Uses a lot of ram, literally a lot even for less number of tabs opened","id":1893080,"status":"UNCONFIRMED","op_sys":"Unspecified","priority":"--"},{"creation_time":"2024-04-25T13:36:23Z","resolution":"","keywords":[],"last_change_time":"2024-06-12T08:36:34Z","severity":"--","summary":"Memory Leak (Isolated Web Container)","component":"Performance","priority":"--","id":1893459,"status":"UNCONFIRMED","op_sys":"Unspecified"},{"resolution":"","keywords":[],"creation_time":"2024-07-19T09:07:38Z","component":"Performance","summary":"www3.nhk.or.jp - The website is loaded after 1-2 seconds of blank page","op_sys":"Windows 11","status":"NEW","id":1908857,"priority":"P3","last_change_time":"2024-09-09T14:01:12Z","severity":"--"},{"summary":"YouTube Freezing and consuming CPU usage","priority":"--","id":1914733,"last_change_time":"2024-09-23T21:20:52Z","resolution":"","keywords":[],"creation_time":"2024-08-24T16:10:13Z","component":"Performance","op_sys":"Unspecified","status":"UNCONFIRMED","severity":"--"},{"priority":"--","id":1918065,"op_sys":"Unspecified","status":"UNCONFIRMED","summary":"High CPU/RAM utilisation using Firefox ESR without internet connectivity","component":"Performance","last_change_time":"2024-09-17T14:48:28Z","severity":"--","keywords":[],"resolution":"","creation_time":"2024-09-11T10:37:14Z"}]}